syslogmp/__init__.py
syslogmp/facility.py
syslogmp/message.py
syslogmp/parser.py
syslogmp/severity.py
syslogmp/stream.py
syslogmp-0.4.dist-info/LICENSE
syslogmp-0.4.dist-info/METADATA
syslogmp-0.4.dist-info/WHEEL
syslogmp-0.4.dist-info/top_level.txt
syslogmp-0.4.dist-info/zip-safe
syslogmp-0.4.dist-info/RECORD
