Metadata-Version: 2.1
Name: syslogmp
Version: 0.4
Summary: A parser for BSD syslog protocol (RFC 3164) messages
Home-page: https://homework.nwsnet.de/releases/76d6/#syslogmp
Author: Jochen Kupperschmidt
Author-email: homework@nwsnet.de
License: MIT
Keywords: irc,webhook
Platform: any
Classifier: Intended Audience :: Developers
Classifier: Intended Audience :: System Administrators
Classifier: License :: OSI Approved :: MIT License
Classifier: Operating System :: OS Independent
Classifier: Programming Language :: Python
Classifier: Programming Language :: Python :: 3
Classifier: Programming Language :: Python :: 3.7
Classifier: Programming Language :: Python :: 3.8
Classifier: Programming Language :: Python :: 3.9
Classifier: Topic :: Communications
Classifier: Topic :: Internet
Classifier: Topic :: System :: Logging
Classifier: Topic :: System :: Networking :: Monitoring
Classifier: Topic :: System :: Systems Administration
Requires-Python: >=3.7
